yxseq/__init__.py
yxseq/cli.py
yxseq/feature.py
yxseq/geneplot.py
yxseq/pipeline.py
yxseq/seq.py
yxseq/versions.py
yxseq-0.0.7.dist-info/LICENSE
yxseq-0.0.7.dist-info/METADATA
yxseq-0.0.7.dist-info/WHEEL
yxseq-0.0.7.dist-info/entry_points.txt
yxseq-0.0.7.dist-info/top_level.txt
yxseq-0.0.7.dist-info/RECORD
